{"stats":{"minecraft:picked_up":{"spartanweaponry:greatsword_iron":1,"minecraft:iron_chestplate":4,"minecraft:creeper_head":1,"iceandfire:copper_ore":8,"minecraft:stone_slab":1,"minecraft:oak_stairs":1,"betteranimalsplus:venisonraw":6,"minecraft:enchanted_book":3,"hexerei:herb_drying_rack_full":1,"minecraft:music_disc_cat":1,"environmental:thief_hood":1,"minecraft:string":10,"silentgear:sinew":2,"iceandfire:myrmex_desert_biolight":5,"aquamirae:dagger_of_greed":1,"minecraft:iron_leggings":1,"minecraft:zombie_head":1,"minecraft:experience_bottle":6,"minecraft:spruce_planks":12,"minecraft:redstone_torch":1,"minecraft:cobblestone_slab":2,"quark:root_item":17,"minecraft:iron_pickaxe":1,"minecraft:iron_boots":2,"minecraft:stick":28,"minecraft:oak_fence":1,"minecraft:torch":27,"epicfight:diamond_greatsword":1,"iceandfire:silver_ore":6,"epicfight:skillbook":8,"minecraft:porkchop":7,"quark:orange_crystal":1,"environmental:dianthus":1,"cavesandcliffs:smooth_basalt":4,"minecraft:orange_bed":1,"hexerei:candelabra":1,"minecraft:stone_sword":1,"minecraft:rotten_flesh":88,"minecraft:tropical_fish":1,"iceandfire:myrmex_desert_chitin":2,"minecraft:cod":1,"quark:marble":76,"minecraft:cobblestone":419,"minecraft:cooked_beef":5,"minecraft:feather":6,"minecraft:andesite":3,"environmental:cattail_seeds":1,"hexerei:willow_fence":4,"minecraft:flint":1,"gobber2:gobber2_ore":5,"minecraft:dirt":50,"cavesandcliffs:glow_ink_sac":1,"environmental:cherries":3,"minecraft:bone":11,"minecraft:chipped_anvil":2,"environmental:cherry_sapling":1,"minecraft:bow":6,"minecraft:wheat_seeds":70,"minecraft:mossy_stone_bricks":1,"minecraft:oak_planks":1,"hexerei:animal_fat":2,"environmental:cherry_log":4,"hexerei:sage":2,"minecraft:sand":7,"iceandfire:stymphalian_bird_feather":3,"minecraft:dead_bush":3,"minecraft:dark_oak_log":19,"minecraft:chiseled_sandstone":1,"iceandfire:myrmex_stinger":2,"minecraft:mossy_cobblestone":1,"quark:cobbled_deepslate":70,"alexsmobs:guster_eye":1,"minecraft:sugar":1,"minecraft:clay":2,"minecraft:diamond":19,"cavesandcliffs:tuff":2,"cavesandcliffs:azalea":1,"minecraft:granite":1,"minecraft:golden_horse_armor":1,"minecraft:emerald":24,"minecraft:bread":78,"minecraft:oak_sapling":5,"minecraft:netherrack":63,"gobber2:gobber2_goo":1,"minecraft:diamond_pickaxe":1,"sophisticatedbackpacks:gold_backpack":1,"iceandfire:cockatrice_eye":1,"minecraft:crafting_table":9,"minecraft:clay_ball":60,"gobber2:gobber2_rod":1,"minecraft:brown_mushroom":1,"minecraft:gold_block":2,"cavesandcliffs:raw_iron":201,"minecraft:chain":2,"gravestone:obituary":5,"minecraft:shield":1,"epicfight:stray_pants":1,"cavesandcliffs:moss_block":4,"minecraft:stone_stairs":1,"iceandfire:frozen_splinters":2,"minecraft:iron_axe":2,"hexerei:crystal_ball":1,"epicfight:stray_hat":1,"minecraft:item_frame":1,"spartanweaponry:battleaxe_iron":3,"epicfight:katana":1,"minecraft:cracked_stone_bricks":1,"minecraft:beef":31,"minecraft:andesite_stairs":1,"minecraft:birch_sapling":2,"minecraft:egg":1,"minecraft:sandstone":11,"aquamirae:shell_horn":1,"minecraft:spruce_fence":1,"sophisticatedbackpacks:backpack":2,"iceandfire:myrmex_resin_desert":4,"minecraft:carrot":2,"minecraft:redstone":35,"minecraft:iron_horse_armor":1,"minecraft:dark_oak_planks":1,"hexerei:sage_seed":2,"iceandfire:cyclops_eye":1,"minecraft:arrow":19,"minecraft:pumpkin_pie":1,"quark:smooth_basalt":9,"minecraft:hay_block":194,"betteranimalsplus:boarhead_dark_brown":1,"aquamirae:treasure_pouch":1,"hexerei:blood_sigil":1,"iceandfire:myrmex_resin_sticky_desert":2,"minecraft:white_wool":3,"minecraft:mutton":32,"minecraft:rail":8,"minecraft:skeleton_skull":2,"minecraft:bone_block":61,"minecraft:oxeye_daisy":2,"minecraft:salmon":1,"minecraft:cut_sandstone":1,"minecraft:leather":19,"minecraft:filled_map":3,"minecraft:oak_log":9,"minecraft:chainmail_chestplate":1,"minecraft:gunpowder":15,"cavesandcliffs:glow_berries":38,"minecraft:white_banner":1,"minecraft:orange_terracotta":4,"minecraft:cooked_mutton":9,"hexerei:willow_stairs":4,"minecraft:stone_bricks":3,"quark:music_disc_crickets":1,"minecraft:kelp":3,"betteranimalsplus:antler":2,"minecraft:iron_ingot":4,"minecraft:iron_ore":16,"minecraft:cooked_chicken":3,"minecraft:cobweb":5,"minecraft:glass_bottle":5,"minecraft:iron_sword":1,"hexerei:mixing_cauldron":1,"cavesandcliffs:calcite":3,"minecraft:dark_oak_slab":1,"cavesandcliffs:cobbled_deepslate":61,"epicfight:stone_greatsword":2,"minecraft:sweet_berries":83,"minecraft:stone_brick_slab":13,"betteranimalsplus:bear_skin_brown":1,"minecraft:gravel":6,"minecraft:spruce_sapling":1,"minecraft:spruce_log":65,"minecraft:gold_ore":18,"betteranimalsplus:turkey_leg_raw":3,"minecraft:spider_eye":6,"minecraft:leather_helmet":2,"betteranimalsplus:eel_meat_raw":4,"hexerei:mahogany_slab":1,"iceandfire:desert_myrmex_cocoon":1,"hexerei:herb_jar":2,"minecraft:iron_helmet":1,"environmental:yak_hair":35,"minecraft:melon_seeds":2,"minecraft:coal":729,"minecraft:ender_pearl":1},"minecraft:crafted":{"minecraft:oak_planks":44,"environmental:cherry_planks":4,"minecraft:cooked_mutton":28,"betteranimalsplus:turkey_leg_cooked":3,"minecraft:iron_boots":4,"silentgear:dried_sinew":1,"minecraft:crafting_table":5,"minecraft:spruce_planks":225,"minecraft:wooden_pickaxe":1,"minecraft:iron_helmet":5,"minecraft:iron_chestplate":6,"minecraft:shield":2,"minecraft:stick":76,"minecraft:iron_ingot":87,"minecraft:iron_pickaxe":7,"minecraft:wooden_sword":1,"minecraft:furnace":4,"gobber2:gobber2_glob":5,"minecraft:iron_axe":2,"minecraft:stone_pickaxe":5,"quark:spruce_chest":2,"minecraft:dark_oak_planks":72,"minecraft:wheat":1170,"sophisticatedbackpacks:iron_backpack":2,"minecraft:cooked_beef":19,"sophisticatedbackpacks:gold_backpack":2,"minecraft:stone_axe":3,"minecraft:bread":390,"minecraft:air":0,"minecraft:wooden_axe":2,"minecraft:iron_leggings":4,"minecraft:torch":144},"minecraft:mined":{"minecraft:dark_oak_planks":1,"hexerei:herb_jar":2,"minecraft:spruce_planks":11,"iceandfire:myrmex_resin_desert":4,"minecraft:andesite_stairs":1,"environmental:dianthus":1,"minecraft:potted_cactus":1,"hexerei:herb_drying_rack_full":1,"minecraft:granite":1,"hexerei:candelabra":1,"minecraft:grass_block":5,"gobber2:gobber2_lucky_block":1,"cavesandcliffs:azalea":1,"minecraft:spawner":24,"environmental:giant_tall_grass":231,"minecraft:tall_seagrass":1,"minecraft:iron_ore":194,"cavesandcliffs:smooth_basalt":4,"environmental:cattail_sprouts":1,"minecraft:oak_stairs":1,"quark:limestone":3,"cavesandcliffs:deepslate_iron_ore":7,"hexerei:willow_leaves":3,"minecraft:orange_bed":1,"minecraft:cut_sandstone":1,"minecraft:brown_mushroom":1,"environmental:tall_cattail":5,"minecraft:orange_terracotta":4,"iceandfire:myrmex_resin_sticky_desert":2,"minecraft:clay":16,"minecraft:torch":4,"quark:orange_crystal":1,"minecraft:dead_bush":4,"minecraft:cobblestone":91,"minecraft:oak_planks":1,"minecraft:wall_torch":11,"minecraft:stone_stairs":1,"minecraft:chain":2,"minecraft:dark_oak_slab":1,"quark:marble":80,"minecraft:wheat":11,"minecraft:blue_ice":1,"cavesandcliffs:deepslate_diamond_ore":11,"cavesandcliffs:tuff":2,"cavesandcliffs:copper_ore":1,"minecraft:grass":51,"minecraft:oak_log":3,"cavesandcliffs:deepslate_redstone_ore":6,"minecraft:sand":5,"minecraft:dirt":15,"cavesandcliffs:deepslate":57,"cavesandcliffs:cobbled_deepslate":2,"minecraft:netherrack":72,"minecraft:oak_leaves":18,"minecraft:diamond_ore":9,"iceandfire:silver_ore":6,"minecraft:mossy_cobblestone":1,"minecraft:dark_oak_log":19,"gravestone:gravestone":49,"minecraft:spruce_fence":1,"hexerei:willow_fence":2,"minecraft:spruce_leaves":6,"minecraft:kelp":4,"minecraft:sandstone":11,"iceandfire:myrmex_desert_biolight":5,"minecraft:large_fern":5,"minecraft:hay_block":132,"minecraft:redstone_ore":2,"cavesandcliffs:cave_vines":28,"iceandfire:copper_ore":8,"hexerei:crystal_ball":1,"minecraft:chiseled_sandstone":1,"minecraft:andesite":4,"quark:smooth_basalt":11,"minecraft:gold_block":2,"minecraft:cobblestone_slab":2,"minecraft:vine":5,"cavesandcliffs:calcite":3,"minecraft:packed_ice":18,"minecraft:stone":352,"minecraft:bone_block":23,"minecraft:stone_brick_slab":13,"minecraft:oak_fence":1,"minecraft:smooth_sandstone":1,"minecraft:crafting_table":9,"hexerei:mahogany_slab":1,"minecraft:emerald_ore":12,"minecraft:stone_slab":1,"minecraft:tall_grass":46,"environmental:cherry_log":5,"cavesandcliffs:deepslate_coal_ore":10,"minecraft:polished_blackstone_stairs":1,"minecraft:sweet_berry_bush":39,"minecraft:spruce_log":64,"quark:deepslate":70,"minecraft:coal_ore":706,"minecraft:gravel":1,"hexerei:willow_stairs":2,"minecraft:cracked_stone_bricks":2,"minecraft:terracotta":1,"minecraft:polished_andesite":1,"minecraft:stone_bricks":3,"minecraft:mossy_stone_bricks":2,"cavesandcliffs:moss_block":2,"minecraft:chipped_anvil":1,"cavesandcliffs:cave_vines_plant":27,"minecraft:fern":8,"quark:root":6},"minecraft:broken":{"minecraft:iron_boots":3,"minecraft:stone_pickaxe":1,"minecraft:wooden_axe":1,"environmental:thief_hood":1,"hexerei:witch_helmet":1,"minecraft:iron_pickaxe":1,"minecraft:iron_helmet":2},"minecraft:custom":{"minecraft:interact_with_crafting_table":55,"minecraft:open_barrel":86,"minecraft:bell_ring":1,"minecraft:leave_game":3,"minecraft:time_since_death":71647,"minecraft:sprint_one_cm":1642434,"minecraft:damage_blocked_by_shield":3519,"minecraft:drop":191,"minecraft:talked_to_villager":7,"minecraft:deaths":56,"minecraft:jump":6832,"minecraft:walk_on_water_one_cm":93011,"minecraft:interact_with_furnace":90,"minecraft:play_one_minute":669302,"minecraft:sleep_in_bed":2,"minecraft:damage_dealt":83052,"minecraft:player_kills":4,"minecraft:crouch_one_cm":62031,"minecraft:interact_with_anvil":3,"minecraft:mob_kills":588,"minecraft:damage_dealt_resisted":1161,"minecraft:climb_one_cm":18550,"minecraft:walk_one_cm":1121793,"minecraft:damage_dealt_absorbed":278,"minecraft:sneak_time":25000,"minecraft:walk_under_water_one_cm":33015,"minecraft:interact_with_grindstone":7,"minecraft:time_since_rest":71700,"minecraft:damage_taken":2147483647,"minecraft:swim_one_cm":139675,"minecraft:fly_one_cm":1720632,"minecraft:open_chest":238,"minecraft:fall_one_cm":157188},"minecraft:used":{"quark:cobbled_deepslate":4,"minecraft:shield":181,"minecraft:iron_sword":152,"epicfight:katana":1244,"environmental:cherry_planks":4,"minecraft:carrot":1,"epicfight:diamond_greatsword":201,"minecraft:stone_bricks":1,"quark:smooth_basalt":1,"minecraft:bow":233,"minecraft:sweet_berries":99,"minecraft:furnace":4,"minecraft:egg":1,"epicfight:skillbook":9,"minecraft:stone_pickaxe":472,"minecraft:oak_planks":4,"minecraft:wooden_pickaxe":46,"cavesandcliffs:cobbled_deepslate":23,"iceandfire:frozen_splinters":2,"minecraft:bread":140,"aquamirae:dagger_of_greed":21,"minecraft:experience_bottle":6,"minecraft:cobweb":1,"minecraft:tropical_fish":1,"spartanweaponry:greatsword_iron":2,"minecraft:spruce_planks":160,"minecraft:cooked_chicken":3,"spartanweaponry:battleaxe_iron":312,"minecraft:netherrack":58,"minecraft:torch":143,"hexerei:coffer":2,"minecraft:dirt":30,"betteranimalsplus:turkey_leg_cooked":3,"minecraft:spruce_fence":1,"minecraft:dark_oak_planks":47,"minecraft:wooden_axe":71,"minecraft:chipped_anvil":1,"quark:spruce_chest":2,"minecraft:iron_axe":209,"epicfight:stone_greatsword":49,"minecraft:cooked_beef":19,"minecraft:cooked_mutton":28,"minecraft:cobblestone_slab":1,"minecraft:salmon":6,"minecraft:crafting_table":14,"minecraft:cod":30,"minecraft:spruce_log":8,"hexerei:herb_drying_rack_full":1,"minecraft:iron_pickaxe":1392,"minecraft:stone_axe":185,"minecraft:cobblestone":342,"alexsmobs:animal_dictionary":2},"minecraft:dropped":{"minecraft:iron_sword":1,"spartanweaponry:greatsword_iron":1,"silentgear:blaze_gold_nugget":8,"minecraft:diamond":6,"hexerei:willow_stairs":4,"minecraft:leather":15,"minecraft:cracked_stone_bricks":1,"minecraft:leather_helmet":2,"minecraft:dirt":18,"hexerei:willow_fence":4,"spartanweaponry:battleaxe_iron":1,"quark:cobbled_deepslate":1,"gravestone:obituary":31,"minecraft:bone_block":13,"minecraft:sand":7,"minecraft:iron_pickaxe":2,"minecraft:white_wool":3,"minecraft:bone":2,"minecraft:gravel":6,"minecraft:stone_axe":1,"quark:root_item":8,"hexerei:blood_sigil":1,"aquamirae:dagger_of_greed":2,"minecraft:birch_sapling":2,"cavesandcliffs:smooth_basalt":4,"cavesandcliffs:moss_block":4,"minecraft:rotten_flesh":22,"quark:orange_crystal":1,"minecraft:stone_stairs":1,"iceandfire:myrmex_resin_desert":4,"minecraft:salmon":21,"minecraft:gunpowder":5,"minecraft:skeleton_skull":1,"minecraft:netherrack":5,"minecraft:iron_ingot":12,"minecraft:bread":206,"cavesandcliffs:cobbled_deepslate":3,"minecraft:wheat_seeds":39,"cavesandcliffs:glow_ink_sac":1,"cavesandcliffs:glow_berries":2,"minecraft:cobblestone":31,"minecraft:oak_fence":1,"minecraft:iron_helmet":2,"minecraft:coal":4,"minecraft:stick":14,"environmental:dianthus":1,"minecraft:cobweb":2,"iceandfire:myrmex_resin_sticky_desert":2,"minecraft:torch":11,"environmental:cherries":3,"minecraft:iron_leggings":3,"epicfight:stone_greatsword":1,"minecraft:iron_axe":1,"minecraft:string":1,"cavesandcliffs:tuff":1,"minecraft:stone_brick_slab":13,"cavesandcliffs:azalea":1,"minecraft:sweet_berries":11,"minecraft:stone_sword":1,"minecraft:clay_ball":16,"minecraft:iron_boots":2,"sophisticatedbackpacks:backpack":1,"epicfight:katana":1,"minecraft:filled_map":3,"minecraft:shield":1,"iceandfire:myrmex_desert_biolight":5,"minecraft:spruce_planks":2,"minecraft:iron_chestplate":3,"minecraft:mossy_stone_bricks":1,"minecraft:andesite_stairs":1,"minecraft:oak_sapling":4,"minecraft:spider_eye":1,"minecraft:stone_bricks":2,"minecraft:bow":2,"minecraft:stone_pickaxe":1,"epicfight:skillbook":1},"minecraft:killed":{"betteranimalsplus:coyote":1,"minecraft:cave_spider":4,"minecraft:witch":15,"betteranimalsplus:turkey":2,"minecraft:spider":9,"iceandfire:stymphalian_bird":3,"betteranimalsplus:moose":1,"quark:forgotten":1,"minecraft:skeleton":33,"minecraft:chicken":1,"betteranimalsplus:goose":1,"betteranimalsplus:goat":6,"iceandfire:myrmex_worker":1,"minecraft:zombie_villager":1,"minecraft:creeper":8,"iceandfire:cockatrice":1,"minecraft:sheep":4,"minecraft:pillager":4,"minecraft:zombie":370,"minecraft:stray":2,"minecraft:cow":4,"minecraft:vindicator":6,"betteranimalsplus:boar":1,"environmental:yak":9,"quark:toretoise":1,"alexsmobs:rattlesnake":1,"minecraft:drowned":1,"iceandfire:deathworm":2,"minecraft:husk":69,"alexsmobs:guster":3,"betteranimalsplus:lamprey":2,"iceandfire:cyclops":1,"minecraft:bat":3,"betteranimalsplus:brownbear":1,"alexsmobs:crocodile":1,"iceandfire:myrmex_soldier":1,"alexsmobs:gazelle":1,"minecraft:enderman":2},"minecraft:killed_by":{"iceandfire:cyclops":9,"minecraft:creeper":1,"minecraft:pillager":1,"alexsmobs:elephant":1,"iceandfire:stymphalian_bird":2,"minecraft:vindicator":5,"alexsmobs:crocodile":1,"aquamirae:captain_cornelia":16,"iceandfire:myrmex_queen":3,"iceandfire:ice_dragon":1,"minecraft:witch":3,"alexsmobs:lobster":1,"iceandfire:myrmex_soldier":2,"iceandfire:fire_dragon":2,"iceandfire:gorgon":3,"alexsmobs:centipede_head":1,"minecraft:skeleton":3,"iceandfire:cockatrice":1}},"DataVersion":2586}